setup.py
dsnd_probability_a0001/Binomialdistribution.py
dsnd_probability_a0001/Gaussiandistribution.py
dsnd_probability_a0001/Generaldistribution.py
dsnd_probability_a0001/__init__.py
dsnd_probability_a0001.egg-info/PKG-INFO
dsnd_probability_a0001.egg-info/SOURCES.txt
dsnd_probability_a0001.egg-info/dependency_links.txt
dsnd_probability_a0001.egg-info/not-zip-safe
dsnd_probability_a0001.egg-info/top_level.txt